us_congress/__init__.py
us_congress/_api/__init__.py
us_congress/_api/fetch.py
us_congress/_api/interface.py
us_congress/_api/models.py
us_congress/_client.py
us_congress/_config.py
us_congress/_exceptions.py
us_congress/_members/interface.py
us_congress/_members/service.py
us_congress/_transformation/__init__.py
us_congress/_transformation/interface.py
us_congress/_transformation/service.py
us_congress/_utils/chunk.py
us_congress/_utils/log/__init__.py
us_congress/_utils/log/configureLogger.py
us_congress/_utils/log/factory.py
us_congress/_utils/log/filters.py
us_congress/_utils/timer.py
us_congress/_utils/unique.py
us_congress/congress.py
us_congress-0.1.2a2.dist-info/LICENSE
us_congress-0.1.2a2.dist-info/WHEEL
us_congress-0.1.2a2.dist-info/METADATA
us_congress-0.1.2a2.dist-info/RECORD
