Metadata-Version: 2.1
Name: us-congress
Version: 0.1.2a2
Summary: Client to work with US Congress data
Home-page: https://github.com/drawjk705/us-congress/
License: MIT
Keywords: US,census
Author: Joel Krim
Author-email: drawjk705@gmail.com
Requires-Python: >=3.9,<4.0
Classifier: License :: OSI Approved :: MIT License
Classifier: Programming Language :: Python :: 3
Classifier: Programming Language :: Python :: 3.9
Classifier: Topic :: Software Development :: Libraries :: Python Modules
Requires-Dist: pandas (>=1.2.0,<2.0.0)
Requires-Dist: punq (>=0.4.1,<0.5.0)
Requires-Dist: python-dotenv (>=0.15.0,<0.16.0)
Requires-Dist: requests (>=2.25.1,<3.0.0)
Requires-Dist: us (>=2.0.2,<3.0.0)
Project-URL: Repository, https://github.com/drawjk705/us-congress/
